Metadata-Version: 1.0
Name: mjoe6-distributions
Version: 0.1
Summary: Gaussian distributions
Home-page: UNKNOWN
Author: Joe McFadden
Author-email: mjoe6@vt.edu
License: UNKNOWN
Platform: UNKNOWN
